twitter_utils/__init__.py
twitter_utils/browser_session.py
twitter_utils/py.typed
twitter_utils/tweets_between.py
twitter_utils/tweets_thread.py
twitter_utils/tweets_writer.py
twitter_utils/twitter_page.py
twitter_utils/twitter_url_builder.py
twitter_utils/workflows/__init__.py
twitter_utils/workflows/workflow_steps.py
twitter_utils-0.5.0.dist-info/entry_points.txt
twitter_utils-0.5.0.dist-info/WHEEL
twitter_utils-0.5.0.dist-info/METADATA
twitter_utils-0.5.0.dist-info/RECORD
