Metadata-Version: 2.1
Name: twitter-utils
Version: 0.5.0
Summary: Collection of twitter utilities.
Home-page: https://namuan.github.io/twitter-utils
License: MIT
Author: namuan
Author-email: github@deskriders.dev
Requires-Python: >=3.7.1,<4.0
Classifier: Development Status :: 4 - Beta
Classifier: Intended Audience :: Developers
Classifier: License :: OSI Approved :: MIT License
Classifier: Operating System :: OS Independent
Classifier: Programming Language :: Python
Classifier: Programming Language :: Python :: 3
Classifier: Programming Language :: Python :: 3.10
Classifier: Programming Language :: Python :: 3.7
Classifier: Programming Language :: Python :: 3.8
Classifier: Programming Language :: Python :: 3.9
Classifier: Topic :: Software Development :: Libraries :: Python Modules
Classifier: Typing :: Typed
Requires-Dist: py-executable-checklist (>=0.10.0,<0.11.0)
Requires-Dist: selenium (>=4.1.0,<5.0.0)
Requires-Dist: slug (>=2.0,<3.0)
Project-URL: Documentation, https://namuan.github.io/twitter-utils
Project-URL: Repository, https://github.com/namuan/twitter-utils
